passgeneration/__init__.py
passgeneration/generate.py
passgeneration-0.0.3.dist-info/LICENSE
passgeneration-0.0.3.dist-info/METADATA
passgeneration-0.0.3.dist-info/WHEEL
passgeneration-0.0.3.dist-info/top_level.txt
passgeneration-0.0.3.dist-info/RECORD
