Metadata-Version: 2.1
Name: passgeneration
Version: 0.0.3
Summary: Password Generating Library. Fixed Name Version
Home-page: https://github.com/Aroko001/PassGeneration-py
Author: aroko900
Author-email: aro0ko1@xmailer.be
License: MIT
Keywords: password generator,password
Classifier: Programming Language :: Python
Classifier: Programming Language :: Python :: 3.10
Classifier: Programming Language :: Python :: 3.11
Classifier: License :: OSI Approved :: MIT License
License-File: LICENSE
